mcp_server_openai/__init__.py
mcp_server_openai/server.py
mcp_server_openai-0.1.4.dist-info/METADATA
mcp_server_openai-0.1.4.dist-info/WHEEL
mcp_server_openai-0.1.4.dist-info/entry_points.txt
mcp_server_openai-0.1.4.dist-info/licenses/LICENSE
mcp_server_openai-0.1.4.dist-info/RECORD
